{
  "dlkdies": {
    "category": "hostile",
    "subtitle": "subtitles.dlkdies",
    "sounds": [
      {
        "name": "tnt_and_disparity:dlkdies",
        "stream": false
      }
    ]
  },
  "dlkhurt": {
    "category": "hostile",
    "subtitle": "subtitles.dlkhurt",
    "sounds": [
      {
        "name": "tnt_and_disparity:dlkhurt",
        "stream": false
      }
    ]
  },
  "dlkdlks": {
    "category": "hostile",
    "subtitle": "subtitles.dlkdlks",
    "sounds": [
      {
        "name": "tnt_and_disparity:dlkdlks",
        "stream": false
      }
    ]
  },
  "ekorekors": {
    "category": "hostile",
    "subtitle": "subtitles.ekorekors",
    "sounds": [
      {
        "name": "tnt_and_disparity:ekorekor",
        "stream": false
      }
    ]
  },
  "dlkkingsaying": {
    "category": "hostile",
    "subtitle": "subtitles.dlkkingsaying",
    "sounds": [
      {
        "name": "tnt_and_disparity:dlkkingsaying",
        "stream": false
      }
    ]
  },
  "dlkkingstickman": {
    "category": "hostile",
    "subtitle": "subtitles.dlkkingstickman",
    "sounds": [
      {
        "name": "tnt_and_disparity:dlkkingstickman",
        "stream": false
      }
    ]
  }
}